ice_g2p/__init__.py
ice_g2p/converter.py
ice_g2p/dictionaries.py
ice_g2p/entry.py
ice_g2p/fetch_models.py
ice_g2p/g2p_lstm.py
ice_g2p/main.py
ice_g2p/stress.py
ice_g2p/syllab_stress_processing.py
ice_g2p/syllabification.py
ice_g2p/syllable.py
ice_g2p/transcriber.py
ice_g2p/tree_builder.py
ice_g2p/trigrams.py
ice_g2p/data/cons_clusters_ipa.txt
ice_g2p/data/cons_clusters_sampa.txt
ice_g2p/data/head_map.csv
ice_g2p/data/modifier_map.csv
ice_g2p/data/sampa_ipa_single_flite.csv
ice_g2p/data/vowels_ipa.txt
ice_g2p/data/vowels_sampa.txt
ice_g2p/dictionaries/ice_pron_dict_english_clear.csv
ice_g2p/dictionaries/ice_pron_dict_north_clear.csv
ice_g2p/dictionaries/ice_pron_dict_standard_clear.csv
ice_g2p/resources/dictionaries/ice_pron_dict_north_clear.csv
ice_g2p/resources/dictionaries/ice_pron_dict_northeast_clear.csv
ice_g2p/resources/dictionaries/ice_pron_dict_south_clear.csv
ice_g2p-1.2.0.dist-info/LICENSE
ice_g2p-1.2.0.dist-info/METADATA
ice_g2p-1.2.0.dist-info/WHEEL
ice_g2p-1.2.0.dist-info/entry_points.txt
ice_g2p-1.2.0.dist-info/top_level.txt
ice_g2p-1.2.0.dist-info/RECORD
