Metadata-Version: 2.1
Name: ice-g2p
Version: 1.2.0
Summary: A grapheme-to-phoneme (g2p) converter for Icelandic
Home-page: https://github.com/grammatek/ice-g2p
Author: Anna Björk Nikulásdóttir
Author-email: anna@grammatek.com
Project-URL: Bug Tracker, https://github.com/grammatek/ice-g2p/issues
Classifier: Programming Language :: Python :: 3
Classifier: License :: OSI Approved :: Apache Software License
Classifier: Operating System :: OS Independent
Classifier: Development Status :: 4 - Beta
Classifier: Intended Audience :: Developers
Classifier: Intended Audience :: Science/Research
Classifier: Topic :: Scientific/Engineering
Classifier: Topic :: Software Development
Classifier: Topic :: Text Processing :: Linguistic
Classifier: Natural Language :: Icelandic
Requires-Python: >=3.6
License-File: LICENSE
Requires-Dist: setuptools
Requires-Dist: importlib-resources
Requires-Dist: torch (>=1.10)
Requires-Dist: fairseq (>=0.10)
Requires-Dist: nltk (>=3.6)
